pypadb/__init__.py
pypadb/setup.py
pypadb/test.py
pypadb/conf/__init__.py
pypadb/conf/db.py
pypadb/conf/table.py
pypadb/connection_pool/__init__.py
pypadb/decorator/__init__.py
pypadb/decorator/delete.py
pypadb/decorator/insert.py
pypadb/decorator/select.py
pypadb/decorator/update.py
pypadb/exception/__init__.py
pypadb/table/__init__.py
pypadb/table/base_table.py
pypadb/utils/__init__.py
pypadb/utils/conditions.py
pypadb/utils/enums.py
pypadb/utils/inspect_util.py
pypadb/utils/query_util.py
pypadb-0.1.14.dist-info/LICENSE
pypadb-0.1.14.dist-info/METADATA
pypadb-0.1.14.dist-info/WHEEL
pypadb-0.1.14.dist-info/top_level.txt
pypadb-0.1.14.dist-info/RECORD
