Metadata-Version: 2.1
Name: pypadb
Version: 0.1.14
Summary: Interaction with database in a simple way
Home-page: https://github.com/ChenzDNA/pypa
Author: ChenzDNA
Author-email: 1007324849@qq.com
License: Apache-2.0
Classifier: Programming Language :: Python :: 3
Classifier: License :: OSI Approved :: Apache Software License
Classifier: Operating System :: OS Independent
Requires-Python: >=3.7.3
License-File: LICENSE
Requires-Dist: DBUtils (>=2.0.2)
Requires-Dist: pydantic (>=1.8.2)
Requires-Dist: PyMySQL (>=1.0.2)
